bioseqtools/__init__.py
bioseqtools/cli.py
bioseqtools/pipelines.py
bioseqtools/versions.py
BioSeqTools-0.3.0.dist-info/LICENSE
BioSeqTools-0.3.0.dist-info/METADATA
BioSeqTools-0.3.0.dist-info/WHEEL
BioSeqTools-0.3.0.dist-info/entry_points.txt
BioSeqTools-0.3.0.dist-info/top_level.txt
BioSeqTools-0.3.0.dist-info/RECORD
